{
  "vite/modulepreload-polyfill": [],
  "node_modules/@unocss/reset/tailwind.css": [],
  "src/styles/main.css": [],
  "src/styles/prose.css": [],
  "src/styles/markdown.css": [],
  "../../../../../__uno.css": [],
  "vite/preload-helper": [],
  "../../../../../@vite-plugin-pages/generated-pages": [],
  "\u0000commonjsHelpers.js": [],
  "\u0000/home/runner/work/Blog/Blog/node_modules/nprogress/nprogress.js?commonjs-module": [],
  "node_modules/nprogress/nprogress.js": [],
  "node_modules/@vue/shared/dist/shared.esm-bundler.js": [],
  "node_modules/@vue/reactivity/dist/reactivity.esm-bundler.js": [],
  "node_modules/@vue/runtime-core/dist/runtime-core.esm-bundler.js": [],
  "node_modules/@vue/runtime-dom/dist/runtime-dom.esm-bundler.js": [],
  "node_modules/vue-router/dist/vue-router.mjs": [],
  "node_modules/@vueuse/head/dist/index.mjs": [],
  "node_modules/vite-ssg/dist/chunks/state.mjs": [],
  "node_modules/vite-ssg/dist/chunks/ClientOnly.mjs": [],
  "node_modules/vite-ssg/dist/index.mjs": [],
  "\u0000/home/runner/work/Blog/Blog/node_modules/dayjs/dayjs.min.js?commonjs-module": [],
  "node_modules/dayjs/dayjs.min.js": [],
  "\u0000/home/runner/work/Blog/Blog/node_modules/dayjs/plugin/localizedFormat.js?commonjs-module": [],
  "node_modules/dayjs/plugin/localizedFormat.js": [],
  "plugin-vue:export-helper": [],
  "src/components/Footer.vue": [],
  "~icons/ri/sun-line": [],
  "~icons/ri/moon-line": [],
  "node_modules/@vueuse/shared/index.mjs": [],
  "node_modules/@vueuse/core/index.mjs": [],
  "src/logics/index.ts": [],
  "src/components/ToggleTheme.vue": [],
  "~icons/uil/github-alt": [],
  "~icons/ri/ball-pen-line": [],
  "~icons/ri/lightbulb-line": [],
  "~icons/ri/article-line": [],
  "../../../../../logo-dark.svg?url": [],
  "../../../../../logo.svg?url": [],
  "src/components/NavBar.vue?vue&type=style&index=0&scoped=true&lang.css": [],
  "src/components/NavBar.vue": [],
  "src/App.vue": [],
  "src/main.ts": [],
  "index.html": [],
  "assets/app.bec8d703.js-unocss-hash.css": [],
  "pages/CLRS.md": [
    "/assets/CLRS.744464d9.js"
  ],
  "src/components/Post.vue": [
    "/assets/Post.67e73c9b.js",
    "/assets/Post.844d8ce7.css"
  ],
  "assets/Post.67e73c9b.js-unocss-hash.css": [
    "/assets/Post.67e73c9b.js",
    "/assets/Post.844d8ce7.css"
  ],
  "src/components/AppLink.vue": [
    "/assets/ListPosts.0b5a21d7.js",
    "/assets/ListPosts.b7c321cb.css"
  ],
  "src/components/ListPosts.vue": [
    "/assets/ListPosts.0b5a21d7.js",
    "/assets/ListPosts.b7c321cb.css"
  ],
  "assets/ListPosts.0b5a21d7.js-unocss-hash.css": [
    "/assets/ListPosts.0b5a21d7.js",
    "/assets/ListPosts.b7c321cb.css"
  ],
  "src/components/Plum.vue": [
    "/assets/Plum.bc881b01.js",
    "/assets/Plum.eacda17b.css"
  ],
  "assets/Plum.bc881b01.js-unocss-hash.css": [
    "/assets/Plum.bc881b01.js",
    "/assets/Plum.eacda17b.css"
  ],
  "pages/[...404].md": [
    "/assets/_...404_.26bfb1e1.js"
  ],
  "pages/algorithm.md": [
    "/assets/algorithm.e2bf3cb5.js"
  ],
  "src/components/SubNav.vue": [
    "/assets/SubNav.86baaee4.js",
    "/assets/SubNav.43c0d90c.css"
  ],
  "assets/SubNav.86baaee4.js-unocss-hash.css": [
    "/assets/SubNav.86baaee4.js",
    "/assets/SubNav.43c0d90c.css"
  ],
  "pages/computer-organization.md": [
    "/assets/computer-organization.cffee6eb.js"
  ],
  "pages/computer-science-notes.md": [
    "/assets/computer-science-notes.1f67b1cd.js"
  ],
  "pages/ds.md": [
    "/assets/ds.6397e61d.js"
  ],
  "public/home.jpg": [
    "/assets/index.b0476292.js",
    "/assets/home.927636e1.jpg"
  ],
  "pages/index.md": [
    "/assets/index.b0476292.js",
    "/assets/home.927636e1.jpg"
  ],
  "pages/leetcode.md": [
    "/assets/leetcode.368bbba5.js"
  ],
  "pages/network.md": [
    "/assets/network.cbac7f2b.js"
  ],
  "pages/notes.md": [
    "/assets/notes.e350f0c4.js"
  ],
  "pages/operating-system.md": [
    "/assets/operating-system.53ea16d9.js"
  ],
  "pages/talks.md": [
    "/assets/talks.ad02d2fe.js"
  ],
  "public/blog.jpg": [
    "/assets/index.0c926fc1.js",
    "/assets/blog.fe91fcc9.jpg"
  ],
  "pages/posts/index.md": [
    "/assets/index.0c926fc1.js",
    "/assets/blog.fe91fcc9.jpg"
  ],
  "pages/posts/algorithm/binary-tree.md": [
    "/assets/binary-tree.c8c64418.js"
  ],
  "public/images/ds/bt/bt-info.jpg": [
    "/assets/bt-info.e1009a26.js",
    "/assets/bt-info.725f0a3d.jpg"
  ],
  "pages/posts/algorithm/bs.md": [
    "/assets/bs.fe34055e.js"
  ],
  "pages/posts/algorithm/dp.md": [
    "/assets/dp.c5ce430f.js"
  ],
  "pages/posts/algorithm/graph.md": [
    "/assets/graph.9634facd.js"
  ],
  "pages/posts/algorithm/greed.md": [
    "/assets/greed.58afa0a1.js"
  ],
  "pages/posts/algorithm/heap.md": [
    "/assets/heap.0ea6df1c.js"
  ],
  "pages/posts/algorithm/linked.md": [
    "/assets/linked.a877b0d2.js"
  ],
  "pages/posts/algorithm/map.md": [
    "/assets/map.e94300f0.js"
  ],
  "public/images/ds/monotonous-stack/monotonous-stack.png": [
    "/assets/monotonous-stack.824170c7.js",
    "/assets/monotonous-stack.1391d708.css",
    "/assets/monotonous-stack.96cf0295.png"
  ],
  "pages/posts/algorithm/monotonous-stack.md": [
    "/assets/monotonous-stack.824170c7.js",
    "/assets/monotonous-stack.1391d708.css",
    "/assets/monotonous-stack.96cf0295.png"
  ],
  "assets/monotonous-stack.824170c7.js-unocss-hash.css": [
    "/assets/monotonous-stack.824170c7.js",
    "/assets/monotonous-stack.1391d708.css",
    "/assets/monotonous-stack.96cf0295.png"
  ],
  "pages/posts/algorithm/queue.md": [
    "/assets/queue.9d75bc1e.js"
  ],
  "pages/posts/algorithm/recursion.md": [
    "/assets/recursion.1ce8f8c6.js"
  ],
  "public/images/ds/sliding-window/demo.drawio.png": [
    "/assets/sliding-window.57fa10ab.js",
    "/assets/demo.drawio.dc205087.png"
  ],
  "pages/posts/algorithm/sliding-window.md": [
    "/assets/sliding-window.57fa10ab.js",
    "/assets/demo.drawio.dc205087.png"
  ],
  "pages/posts/algorithm/sort.md": [
    "/assets/sort.9bd48766.js"
  ],
  "pages/posts/algorithm/stack.md": [
    "/assets/stack.35bd591c.js"
  ],
  "public/images/ds/trie.png": [
    "/assets/trie.59227a45.js",
    "/assets/trie.54a180c1.png"
  ],
  "pages/posts/algorithm/trie.md": [
    "/assets/trie.59227a45.js",
    "/assets/trie.54a180c1.png"
  ],
  "pages/posts/algorithm/union-set.md": [
    "/assets/union-set.987b60e8.js"
  ],
  "pages/posts/algorithm/xor.md": [
    "/assets/xor.c938b341.js"
  ],
  "pages/posts/blog/arraytomap.md": [
    "/assets/arraytomap.4d41c6e4.js"
  ],
  "pages/posts/computer-organization/02-machine-level-representation-of-data.md": [
    "/assets/02-machine-level-representation-of-data.0c25de06.js"
  ],
  "public/images/computer-science-notes/1.1.png": [
    "/assets/computer-science-notes-chapter01.8dd76e51.js",
    "/assets/1.1.d7581ca9.png",
    "/assets/1.2.534131d5.png",
    "/assets/1.3.ac82f536.png"
  ],
  "public/images/computer-science-notes/1.2.png": [
    "/assets/computer-science-notes-chapter01.8dd76e51.js",
    "/assets/1.1.d7581ca9.png",
    "/assets/1.2.534131d5.png",
    "/assets/1.3.ac82f536.png"
  ],
  "public/images/computer-science-notes/1.3.png": [
    "/assets/computer-science-notes-chapter01.8dd76e51.js",
    "/assets/1.1.d7581ca9.png",
    "/assets/1.2.534131d5.png",
    "/assets/1.3.ac82f536.png"
  ],
  "pages/posts/computer-science-notes/computer-science-notes-chapter01.md": [
    "/assets/computer-science-notes-chapter01.8dd76e51.js",
    "/assets/1.1.d7581ca9.png",
    "/assets/1.2.534131d5.png",
    "/assets/1.3.ac82f536.png"
  ],
  "public/images/computer-science-notes/2.1.png": [
    "/assets/computer-science-notes-chapter02.ae5bd606.js",
    "/assets/computer-science-notes-chapter02.a559d910.css",
    "/assets/2.1.75dc0817.png",
    "/assets/2.2.b916cec9.png",
    "/assets/2.3.1036ce41.png",
    "/assets/2.4.e0b631ce.png",
    "/assets/2.5.6d4102c4.png",
    "/assets/2.6.7120d38c.png",
    "/assets/2.7.f19428b8.png",
    "/assets/2.8.c0f15436.png",
    "/assets/2.9.d40df940.png",
    "/assets/2.10.de08090e.png"
  ],
  "public/images/computer-science-notes/2.2.png": [
    "/assets/computer-science-notes-chapter02.ae5bd606.js",
    "/assets/computer-science-notes-chapter02.a559d910.css",
    "/assets/2.1.75dc0817.png",
    "/assets/2.2.b916cec9.png",
    "/assets/2.3.1036ce41.png",
    "/assets/2.4.e0b631ce.png",
    "/assets/2.5.6d4102c4.png",
    "/assets/2.6.7120d38c.png",
    "/assets/2.7.f19428b8.png",
    "/assets/2.8.c0f15436.png",
    "/assets/2.9.d40df940.png",
    "/assets/2.10.de08090e.png"
  ],
  "public/images/computer-science-notes/2.3.png": [
    "/assets/computer-science-notes-chapter02.ae5bd606.js",
    "/assets/computer-science-notes-chapter02.a559d910.css",
    "/assets/2.1.75dc0817.png",
    "/assets/2.2.b916cec9.png",
    "/assets/2.3.1036ce41.png",
    "/assets/2.4.e0b631ce.png",
    "/assets/2.5.6d4102c4.png",
    "/assets/2.6.7120d38c.png",
    "/assets/2.7.f19428b8.png",
    "/assets/2.8.c0f15436.png",
    "/assets/2.9.d40df940.png",
    "/assets/2.10.de08090e.png"
  ],
  "public/images/computer-science-notes/2.4.png": [
    "/assets/computer-science-notes-chapter02.ae5bd606.js",
    "/assets/computer-science-notes-chapter02.a559d910.css",
    "/assets/2.1.75dc0817.png",
    "/assets/2.2.b916cec9.png",
    "/assets/2.3.1036ce41.png",
    "/assets/2.4.e0b631ce.png",
    "/assets/2.5.6d4102c4.png",
    "/assets/2.6.7120d38c.png",
    "/assets/2.7.f19428b8.png",
    "/assets/2.8.c0f15436.png",
    "/assets/2.9.d40df940.png",
    "/assets/2.10.de08090e.png"
  ],
  "public/images/computer-science-notes/2.5.png": [
    "/assets/computer-science-notes-chapter02.ae5bd606.js",
    "/assets/computer-science-notes-chapter02.a559d910.css",
    "/assets/2.1.75dc0817.png",
    "/assets/2.2.b916cec9.png",
    "/assets/2.3.1036ce41.png",
    "/assets/2.4.e0b631ce.png",
    "/assets/2.5.6d4102c4.png",
    "/assets/2.6.7120d38c.png",
    "/assets/2.7.f19428b8.png",
    "/assets/2.8.c0f15436.png",
    "/assets/2.9.d40df940.png",
    "/assets/2.10.de08090e.png"
  ],
  "public/images/computer-science-notes/2.6.png": [
    "/assets/computer-science-notes-chapter02.ae5bd606.js",
    "/assets/computer-science-notes-chapter02.a559d910.css",
    "/assets/2.1.75dc0817.png",
    "/assets/2.2.b916cec9.png",
    "/assets/2.3.1036ce41.png",
    "/assets/2.4.e0b631ce.png",
    "/assets/2.5.6d4102c4.png",
    "/assets/2.6.7120d38c.png",
    "/assets/2.7.f19428b8.png",
    "/assets/2.8.c0f15436.png",
    "/assets/2.9.d40df940.png",
    "/assets/2.10.de08090e.png"
  ],
  "public/images/computer-science-notes/2.7.png": [
    "/assets/computer-science-notes-chapter02.ae5bd606.js",
    "/assets/computer-science-notes-chapter02.a559d910.css",
    "/assets/2.1.75dc0817.png",
    "/assets/2.2.b916cec9.png",
    "/assets/2.3.1036ce41.png",
    "/assets/2.4.e0b631ce.png",
    "/assets/2.5.6d4102c4.png",
    "/assets/2.6.7120d38c.png",
    "/assets/2.7.f19428b8.png",
    "/assets/2.8.c0f15436.png",
    "/assets/2.9.d40df940.png",
    "/assets/2.10.de08090e.png"
  ],
  "public/images/computer-science-notes/2.8.png": [
    "/assets/computer-science-notes-chapter02.ae5bd606.js",
    "/assets/computer-science-notes-chapter02.a559d910.css",
    "/assets/2.1.75dc0817.png",
    "/assets/2.2.b916cec9.png",
    "/assets/2.3.1036ce41.png",
    "/assets/2.4.e0b631ce.png",
    "/assets/2.5.6d4102c4.png",
    "/assets/2.6.7120d38c.png",
    "/assets/2.7.f19428b8.png",
    "/assets/2.8.c0f15436.png",
    "/assets/2.9.d40df940.png",
    "/assets/2.10.de08090e.png"
  ],
  "public/images/computer-science-notes/2.9.png": [
    "/assets/computer-science-notes-chapter02.ae5bd606.js",
    "/assets/computer-science-notes-chapter02.a559d910.css",
    "/assets/2.1.75dc0817.png",
    "/assets/2.2.b916cec9.png",
    "/assets/2.3.1036ce41.png",
    "/assets/2.4.e0b631ce.png",
    "/assets/2.5.6d4102c4.png",
    "/assets/2.6.7120d38c.png",
    "/assets/2.7.f19428b8.png",
    "/assets/2.8.c0f15436.png",
    "/assets/2.9.d40df940.png",
    "/assets/2.10.de08090e.png"
  ],
  "public/images/computer-science-notes/2.10.png": [
    "/assets/computer-science-notes-chapter02.ae5bd606.js",
    "/assets/computer-science-notes-chapter02.a559d910.css",
    "/assets/2.1.75dc0817.png",
    "/assets/2.2.b916cec9.png",
    "/assets/2.3.1036ce41.png",
    "/assets/2.4.e0b631ce.png",
    "/assets/2.5.6d4102c4.png",
    "/assets/2.6.7120d38c.png",
    "/assets/2.7.f19428b8.png",
    "/assets/2.8.c0f15436.png",
    "/assets/2.9.d40df940.png",
    "/assets/2.10.de08090e.png"
  ],
  "pages/posts/computer-science-notes/computer-science-notes-chapter02.md": [
    "/assets/computer-science-notes-chapter02.ae5bd606.js",
    "/assets/computer-science-notes-chapter02.a559d910.css",
    "/assets/2.1.75dc0817.png",
    "/assets/2.2.b916cec9.png",
    "/assets/2.3.1036ce41.png",
    "/assets/2.4.e0b631ce.png",
    "/assets/2.5.6d4102c4.png",
    "/assets/2.6.7120d38c.png",
    "/assets/2.7.f19428b8.png",
    "/assets/2.8.c0f15436.png",
    "/assets/2.9.d40df940.png",
    "/assets/2.10.de08090e.png"
  ],
  "assets/computer-science-notes-chapter02.ae5bd606.js-unocss-hash.css": [
    "/assets/computer-science-notes-chapter02.ae5bd606.js",
    "/assets/computer-science-notes-chapter02.a559d910.css",
    "/assets/2.1.75dc0817.png",
    "/assets/2.2.b916cec9.png",
    "/assets/2.3.1036ce41.png",
    "/assets/2.4.e0b631ce.png",
    "/assets/2.5.6d4102c4.png",
    "/assets/2.6.7120d38c.png",
    "/assets/2.7.f19428b8.png",
    "/assets/2.8.c0f15436.png",
    "/assets/2.9.d40df940.png",
    "/assets/2.10.de08090e.png"
  ],
  "pages/posts/computer-science-notes/computer-science-notes-chapter03.md": [
    "/assets/computer-science-notes-chapter03.75c16010.js"
  ],
  "pages/posts/computer-science-notes/computer-science-notes-chapter04.md": [
    "/assets/computer-science-notes-chapter04.47590a95.js"
  ],
  "pages/posts/computer-science-notes/computer-science-notes-chapter05.md": [
    "/assets/computer-science-notes-chapter05.0e475ebe.js"
  ],
  "public/images/computer-science-notes/6.2.png": [
    "/assets/computer-science-notes-chapter06.49878081.js",
    "/assets/6.2.acc7e79e.png",
    "/assets/6.1.aaa4faaf.png",
    "/assets/6.4.6e15717d.png",
    "/assets/6.5.fe1d4e2b.png",
    "/assets/6.6.c734c5a6.png"
  ],
  "public/images/computer-science-notes/6.1.png": [
    "/assets/computer-science-notes-chapter06.49878081.js",
    "/assets/6.2.acc7e79e.png",
    "/assets/6.1.aaa4faaf.png",
    "/assets/6.4.6e15717d.png",
    "/assets/6.5.fe1d4e2b.png",
    "/assets/6.6.c734c5a6.png"
  ],
  "public/images/computer-science-notes/6.4.png": [
    "/assets/computer-science-notes-chapter06.49878081.js",
    "/assets/6.2.acc7e79e.png",
    "/assets/6.1.aaa4faaf.png",
    "/assets/6.4.6e15717d.png",
    "/assets/6.5.fe1d4e2b.png",
    "/assets/6.6.c734c5a6.png"
  ],
  "public/images/computer-science-notes/6.5.png": [
    "/assets/computer-science-notes-chapter06.49878081.js",
    "/assets/6.2.acc7e79e.png",
    "/assets/6.1.aaa4faaf.png",
    "/assets/6.4.6e15717d.png",
    "/assets/6.5.fe1d4e2b.png",
    "/assets/6.6.c734c5a6.png"
  ],
  "public/images/computer-science-notes/6.6.png": [
    "/assets/computer-science-notes-chapter06.49878081.js",
    "/assets/6.2.acc7e79e.png",
    "/assets/6.1.aaa4faaf.png",
    "/assets/6.4.6e15717d.png",
    "/assets/6.5.fe1d4e2b.png",
    "/assets/6.6.c734c5a6.png"
  ],
  "pages/posts/computer-science-notes/computer-science-notes-chapter06.md": [
    "/assets/computer-science-notes-chapter06.49878081.js",
    "/assets/6.2.acc7e79e.png",
    "/assets/6.1.aaa4faaf.png",
    "/assets/6.4.6e15717d.png",
    "/assets/6.5.fe1d4e2b.png",
    "/assets/6.6.c734c5a6.png"
  ],
  "public/images/computer-science-notes/7.1.png": [
    "/assets/computer-science-notes-chapter07.73454f0b.js",
    "/assets/7.1.e68063e6.png",
    "/assets/7.2.7bab15fd.png"
  ],
  "public/images/computer-science-notes/7.2.png": [
    "/assets/computer-science-notes-chapter07.73454f0b.js",
    "/assets/7.1.e68063e6.png",
    "/assets/7.2.7bab15fd.png"
  ],
  "pages/posts/computer-science-notes/computer-science-notes-chapter07.md": [
    "/assets/computer-science-notes-chapter07.73454f0b.js",
    "/assets/7.1.e68063e6.png",
    "/assets/7.2.7bab15fd.png"
  ],
  "public/images/computer-science-notes/8.1.png": [
    "/assets/computer-science-notes-chapter08.df0c14c2.js",
    "/assets/8.1.ed549f68.png",
    "/assets/8.2.a26bf0a5.png",
    "/assets/8.3.265e863d.png",
    "/assets/8.4.401f6dc9.png",
    "/assets/8.5.ed2c25e3.png",
    "/assets/8.6.afc79e08.png",
    "/assets/8.7.f2a073ab.png"
  ],
  "public/images/computer-science-notes/8.2.png": [
    "/assets/computer-science-notes-chapter08.df0c14c2.js",
    "/assets/8.1.ed549f68.png",
    "/assets/8.2.a26bf0a5.png",
    "/assets/8.3.265e863d.png",
    "/assets/8.4.401f6dc9.png",
    "/assets/8.5.ed2c25e3.png",
    "/assets/8.6.afc79e08.png",
    "/assets/8.7.f2a073ab.png"
  ],
  "public/images/computer-science-notes/8.3.png": [
    "/assets/computer-science-notes-chapter08.df0c14c2.js",
    "/assets/8.1.ed549f68.png",
    "/assets/8.2.a26bf0a5.png",
    "/assets/8.3.265e863d.png",
    "/assets/8.4.401f6dc9.png",
    "/assets/8.5.ed2c25e3.png",
    "/assets/8.6.afc79e08.png",
    "/assets/8.7.f2a073ab.png"
  ],
  "public/images/computer-science-notes/8.4.png": [
    "/assets/computer-science-notes-chapter08.df0c14c2.js",
    "/assets/8.1.ed549f68.png",
    "/assets/8.2.a26bf0a5.png",
    "/assets/8.3.265e863d.png",
    "/assets/8.4.401f6dc9.png",
    "/assets/8.5.ed2c25e3.png",
    "/assets/8.6.afc79e08.png",
    "/assets/8.7.f2a073ab.png"
  ],
  "public/images/computer-science-notes/8.5.png": [
    "/assets/computer-science-notes-chapter08.df0c14c2.js",
    "/assets/8.1.ed549f68.png",
    "/assets/8.2.a26bf0a5.png",
    "/assets/8.3.265e863d.png",
    "/assets/8.4.401f6dc9.png",
    "/assets/8.5.ed2c25e3.png",
    "/assets/8.6.afc79e08.png",
    "/assets/8.7.f2a073ab.png"
  ],
  "public/images/computer-science-notes/8.6.png": [
    "/assets/computer-science-notes-chapter08.df0c14c2.js",
    "/assets/8.1.ed549f68.png",
    "/assets/8.2.a26bf0a5.png",
    "/assets/8.3.265e863d.png",
    "/assets/8.4.401f6dc9.png",
    "/assets/8.5.ed2c25e3.png",
    "/assets/8.6.afc79e08.png",
    "/assets/8.7.f2a073ab.png"
  ],
  "public/images/computer-science-notes/8.7.png": [
    "/assets/computer-science-notes-chapter08.df0c14c2.js",
    "/assets/8.1.ed549f68.png",
    "/assets/8.2.a26bf0a5.png",
    "/assets/8.3.265e863d.png",
    "/assets/8.4.401f6dc9.png",
    "/assets/8.5.ed2c25e3.png",
    "/assets/8.6.afc79e08.png",
    "/assets/8.7.f2a073ab.png"
  ],
  "pages/posts/computer-science-notes/computer-science-notes-chapter08.md": [
    "/assets/computer-science-notes-chapter08.df0c14c2.js",
    "/assets/8.1.ed549f68.png",
    "/assets/8.2.a26bf0a5.png",
    "/assets/8.3.265e863d.png",
    "/assets/8.4.401f6dc9.png",
    "/assets/8.5.ed2c25e3.png",
    "/assets/8.6.afc79e08.png",
    "/assets/8.7.f2a073ab.png"
  ],
  "public/images/computer-science-notes/9.1.png": [
    "/assets/computer-science-notes-chapter09.e2e0cea2.js",
    "/assets/9.1.db5c4e50.png",
    "/assets/9.2.0c9336a6.png",
    "/assets/9.3.82a7c35d.png",
    "/assets/9.4.d0f2ff56.png"
  ],
  "public/images/computer-science-notes/9.2.png": [
    "/assets/computer-science-notes-chapter09.e2e0cea2.js",
    "/assets/9.1.db5c4e50.png",
    "/assets/9.2.0c9336a6.png",
    "/assets/9.3.82a7c35d.png",
    "/assets/9.4.d0f2ff56.png"
  ],
  "public/images/computer-science-notes/9.3.png": [
    "/assets/computer-science-notes-chapter09.e2e0cea2.js",
    "/assets/9.1.db5c4e50.png",
    "/assets/9.2.0c9336a6.png",
    "/assets/9.3.82a7c35d.png",
    "/assets/9.4.d0f2ff56.png"
  ],
  "public/images/computer-science-notes/9.4.png": [
    "/assets/computer-science-notes-chapter09.e2e0cea2.js",
    "/assets/9.1.db5c4e50.png",
    "/assets/9.2.0c9336a6.png",
    "/assets/9.3.82a7c35d.png",
    "/assets/9.4.d0f2ff56.png"
  ],
  "pages/posts/computer-science-notes/computer-science-notes-chapter09.md": [
    "/assets/computer-science-notes-chapter09.e2e0cea2.js",
    "/assets/9.1.db5c4e50.png",
    "/assets/9.2.0c9336a6.png",
    "/assets/9.3.82a7c35d.png",
    "/assets/9.4.d0f2ff56.png"
  ],
  "public/images/computer-science-notes/10.1.png": [
    "/assets/computer-science-notes-chapter10.f98f5717.js",
    "/assets/10.1.dbfb8bb8.png",
    "/assets/10.2.7d36355b.png",
    "/assets/10.3.99b2be00.png",
    "/assets/10.4.85fddecf.png",
    "/assets/10.5.6a6ae986.png"
  ],
  "public/images/computer-science-notes/10.2.png": [
    "/assets/computer-science-notes-chapter10.f98f5717.js",
    "/assets/10.1.dbfb8bb8.png",
    "/assets/10.2.7d36355b.png",
    "/assets/10.3.99b2be00.png",
    "/assets/10.4.85fddecf.png",
    "/assets/10.5.6a6ae986.png"
  ],
  "public/images/computer-science-notes/10.3.png": [
    "/assets/computer-science-notes-chapter10.f98f5717.js",
    "/assets/10.1.dbfb8bb8.png",
    "/assets/10.2.7d36355b.png",
    "/assets/10.3.99b2be00.png",
    "/assets/10.4.85fddecf.png",
    "/assets/10.5.6a6ae986.png"
  ],
  "public/images/computer-science-notes/10.4.png": [
    "/assets/computer-science-notes-chapter10.f98f5717.js",
    "/assets/10.1.dbfb8bb8.png",
    "/assets/10.2.7d36355b.png",
    "/assets/10.3.99b2be00.png",
    "/assets/10.4.85fddecf.png",
    "/assets/10.5.6a6ae986.png"
  ],
  "public/images/computer-science-notes/10.5.png": [
    "/assets/computer-science-notes-chapter10.f98f5717.js",
    "/assets/10.1.dbfb8bb8.png",
    "/assets/10.2.7d36355b.png",
    "/assets/10.3.99b2be00.png",
    "/assets/10.4.85fddecf.png",
    "/assets/10.5.6a6ae986.png"
  ],
  "pages/posts/computer-science-notes/computer-science-notes-chapter10.md": [
    "/assets/computer-science-notes-chapter10.f98f5717.js",
    "/assets/10.1.dbfb8bb8.png",
    "/assets/10.2.7d36355b.png",
    "/assets/10.3.99b2be00.png",
    "/assets/10.4.85fddecf.png",
    "/assets/10.5.6a6ae986.png"
  ],
  "public/images/computer-science-notes/11.1.png": [
    "/assets/computer-science-notes-chapter11.6f7e92c6.js",
    "/assets/11.1.ff7b8318.png",
    "/assets/11.2.1018c5da.png"
  ],
  "public/images/computer-science-notes/11.2.png": [
    "/assets/computer-science-notes-chapter11.6f7e92c6.js",
    "/assets/11.1.ff7b8318.png",
    "/assets/11.2.1018c5da.png"
  ],
  "pages/posts/computer-science-notes/computer-science-notes-chapter11.md": [
    "/assets/computer-science-notes-chapter11.6f7e92c6.js",
    "/assets/11.1.ff7b8318.png",
    "/assets/11.2.1018c5da.png"
  ],
  "pages/posts/computer-science-notes/computer-science-notes-chapter12.md": [
    "/assets/computer-science-notes-chapter12.98f2f0b3.js"
  ],
  "public/images/computer-science-notes/13.1.png": [
    "/assets/computer-science-notes-chapter13.a3dcf5cc.js",
    "/assets/13.1.fae928fa.png",
    "/assets/13.2.a895fca4.png",
    "/assets/13.3.eb003e5c.png",
    "/assets/13.4.f752229e.png",
    "/assets/13.5.9ef718c8.png",
    "/assets/13.6.f846057d.png"
  ],
  "public/images/computer-science-notes/13.2.png": [
    "/assets/computer-science-notes-chapter13.a3dcf5cc.js",
    "/assets/13.1.fae928fa.png",
    "/assets/13.2.a895fca4.png",
    "/assets/13.3.eb003e5c.png",
    "/assets/13.4.f752229e.png",
    "/assets/13.5.9ef718c8.png",
    "/assets/13.6.f846057d.png"
  ],
  "public/images/computer-science-notes/13.3.png": [
    "/assets/computer-science-notes-chapter13.a3dcf5cc.js",
    "/assets/13.1.fae928fa.png",
    "/assets/13.2.a895fca4.png",
    "/assets/13.3.eb003e5c.png",
    "/assets/13.4.f752229e.png",
    "/assets/13.5.9ef718c8.png",
    "/assets/13.6.f846057d.png"
  ],
  "public/images/computer-science-notes/13.4.png": [
    "/assets/computer-science-notes-chapter13.a3dcf5cc.js",
    "/assets/13.1.fae928fa.png",
    "/assets/13.2.a895fca4.png",
    "/assets/13.3.eb003e5c.png",
    "/assets/13.4.f752229e.png",
    "/assets/13.5.9ef718c8.png",
    "/assets/13.6.f846057d.png"
  ],
  "public/images/computer-science-notes/13.5.png": [
    "/assets/computer-science-notes-chapter13.a3dcf5cc.js",
    "/assets/13.1.fae928fa.png",
    "/assets/13.2.a895fca4.png",
    "/assets/13.3.eb003e5c.png",
    "/assets/13.4.f752229e.png",
    "/assets/13.5.9ef718c8.png",
    "/assets/13.6.f846057d.png"
  ],
  "public/images/computer-science-notes/13.6.png": [
    "/assets/computer-science-notes-chapter13.a3dcf5cc.js",
    "/assets/13.1.fae928fa.png",
    "/assets/13.2.a895fca4.png",
    "/assets/13.3.eb003e5c.png",
    "/assets/13.4.f752229e.png",
    "/assets/13.5.9ef718c8.png",
    "/assets/13.6.f846057d.png"
  ],
  "pages/posts/computer-science-notes/computer-science-notes-chapter13.md": [
    "/assets/computer-science-notes-chapter13.a3dcf5cc.js",
    "/assets/13.1.fae928fa.png",
    "/assets/13.2.a895fca4.png",
    "/assets/13.3.eb003e5c.png",
    "/assets/13.4.f752229e.png",
    "/assets/13.5.9ef718c8.png",
    "/assets/13.6.f846057d.png"
  ],
  "pages/posts/computer-science-notes/computer-science-notes-chapter14.md": [
    "/assets/computer-science-notes-chapter14.9bb33e84.js"
  ],
  "public/images/computer-science-notes/15.1.png": [
    "/assets/computer-science-notes-chapter15.38a3e5fb.js",
    "/assets/15.1.241b4513.png",
    "/assets/15.2.2a4d7045.png"
  ],
  "public/images/computer-science-notes/15.2.png": [
    "/assets/computer-science-notes-chapter15.38a3e5fb.js",
    "/assets/15.1.241b4513.png",
    "/assets/15.2.2a4d7045.png"
  ],
  "pages/posts/computer-science-notes/computer-science-notes-chapter15.md": [
    "/assets/computer-science-notes-chapter15.38a3e5fb.js",
    "/assets/15.1.241b4513.png",
    "/assets/15.2.2a4d7045.png"
  ],
  "public/images/computer-science-notes/16.1.png": [
    "/assets/computer-science-notes-chapter16.ad96ccc7.js",
    "/assets/16.1.0ec85a80.png"
  ],
  "pages/posts/computer-science-notes/computer-science-notes-chapter16.md": [
    "/assets/computer-science-notes-chapter16.ad96ccc7.js",
    "/assets/16.1.0ec85a80.png"
  ],
  "public/images/computer-science-notes/17.1.png": [
    "/assets/computer-science-notes-chapter17.6db497aa.js",
    "/assets/17.1.549fa5a9.png",
    "/assets/17.2.93535636.png"
  ],
  "public/images/computer-science-notes/17.2.png": [
    "/assets/computer-science-notes-chapter17.6db497aa.js",
    "/assets/17.1.549fa5a9.png",
    "/assets/17.2.93535636.png"
  ],
  "pages/posts/computer-science-notes/computer-science-notes-chapter17.md": [
    "/assets/computer-science-notes-chapter17.6db497aa.js",
    "/assets/17.1.549fa5a9.png",
    "/assets/17.2.93535636.png"
  ],
  "pages/posts/ds/linear-list.md": [
    "/assets/linear-list.f4531419.js"
  ],
  "pages/posts/leetcode/01-array.md": [
    "/assets/01-array.2732c33d.js"
  ],
  "pages/posts/talk/00-godoc.md": [
    "/assets/00-godoc.2b8d4a36.js"
  ],
  "pages/posts/talk/01-MongoDB.md": [
    "/assets/01-MongoDB.a7c29f0b.js"
  ],
  "pages/posts/talk/03-ZooKeeper.md": [
    "/assets/03-ZooKeeper.ec6e2476.js"
  ],
  "pages/posts/talk/04-Redis.md": [
    "/assets/04-Redis.4e3413a8.js"
  ],
  "pages/posts/talk/05-vite-path.md": [
    "/assets/05-vite-path.2c0706fc.js"
  ],
  "public/images/talks/vue-router-1.png": [
    "/assets/06-vue-router4.9064577c.js",
    "/assets/vue-router-1.f6cb482c.png"
  ],
  "pages/posts/talk/06-vue-router4.md": [
    "/assets/06-vue-router4.9064577c.js",
    "/assets/vue-router-1.f6cb482c.png"
  ],
  "pages/posts/talk/07-go-modules.md": [
    "/assets/07-go-modules.e929d62a.js"
  ],
  "pages/posts/talk/08-scrapy.md": [
    "/assets/08-scrapy.545601bb.js"
  ],
  "pages/posts/talk/09-java-springboot-websocket.md": [
    "/assets/09-java-springboot-websocket.311e8148.js",
    "/assets/monotonous-stack.1391d708.css"
  ],
  "assets/09-java-springboot-websocket.311e8148.js-unocss-hash.css": [
    "/assets/09-java-springboot-websocket.311e8148.js",
    "/assets/monotonous-stack.1391d708.css"
  ],
  "pages/posts/talk/11-mac-graalvm.md": [
    "/assets/11-mac-graalvm.4c0100a7.js"
  ],
  "pages/posts/talk/12-naven-orgin.md": [
    "/assets/12-naven-orgin.01c4ce0e.js"
  ],
  "pages/posts/talk/13-mac-cmd.md": [
    "/assets/13-mac-cmd.39ac5874.js"
  ],
  "public/images/talks/c-408/c-scanf.png": [
    "/assets/c-001-scanf.0abc3df9.js",
    "/assets/c-scanf.8db0f638.png",
    "/assets/c-scanf-2.9339ca6d.png"
  ],
  "public/images/talks/c-408/c-scanf-2.png": [
    "/assets/c-001-scanf.0abc3df9.js",
    "/assets/c-scanf.8db0f638.png",
    "/assets/c-scanf-2.9339ca6d.png"
  ],
  "pages/posts/talk/c-001-scanf.md": [
    "/assets/c-001-scanf.0abc3df9.js",
    "/assets/c-scanf.8db0f638.png",
    "/assets/c-scanf-2.9339ca6d.png"
  ],
  "public/images/talks/c-408/c-heap-stack-differ.png": [
    "/assets/c-002-pointer.1e832625.js",
    "/assets/c-heap-stack-differ.5dfa9586.png"
  ],
  "pages/posts/talk/c-002-pointer.md": [
    "/assets/c-002-pointer.1e832625.js",
    "/assets/c-heap-stack-differ.5dfa9586.png"
  ],
  "public/images/talks/c-408/c-struct-0.png": [
    "/assets/c-003-struct-align.9a454f46.js",
    "/assets/c-struct-0.aaa3b9e8.png",
    "/assets/c-struct-1.e3d6c98b.png",
    "/assets/c-struct-2.4b545aa8.png",
    "/assets/c-struct-3.f169a55d.png"
  ],
  "public/images/talks/c-408/c-struct-1.png": [
    "/assets/c-003-struct-align.9a454f46.js",
    "/assets/c-struct-0.aaa3b9e8.png",
    "/assets/c-struct-1.e3d6c98b.png",
    "/assets/c-struct-2.4b545aa8.png",
    "/assets/c-struct-3.f169a55d.png"
  ],
  "public/images/talks/c-408/c-struct-2.png": [
    "/assets/c-003-struct-align.9a454f46.js",
    "/assets/c-struct-0.aaa3b9e8.png",
    "/assets/c-struct-1.e3d6c98b.png",
    "/assets/c-struct-2.4b545aa8.png",
    "/assets/c-struct-3.f169a55d.png"
  ],
  "public/images/talks/c-408/c-struct-3.png": [
    "/assets/c-003-struct-align.9a454f46.js",
    "/assets/c-struct-0.aaa3b9e8.png",
    "/assets/c-struct-1.e3d6c98b.png",
    "/assets/c-struct-2.4b545aa8.png",
    "/assets/c-struct-3.f169a55d.png"
  ],
  "pages/posts/talk/c-003-struct-align.md": [
    "/assets/c-003-struct-align.9a454f46.js",
    "/assets/c-struct-0.aaa3b9e8.png",
    "/assets/c-struct-1.e3d6c98b.png",
    "/assets/c-struct-2.4b545aa8.png",
    "/assets/c-struct-3.f169a55d.png"
  ],
  "pages/posts/algorithm/binary-tree-posts/2023-09-05-bs-1.md": [
    "/assets/2023-09-05-bs-1.f35795d3.js",
    "/assets/monotonous-stack.1391d708.css"
  ],
  "assets/2023-09-05-bs-1.f35795d3.js-unocss-hash.css": [
    "/assets/2023-09-05-bs-1.f35795d3.js",
    "/assets/monotonous-stack.1391d708.css"
  ],
  "pages/posts/algorithm/binary-tree-posts/2023-09-05-bs-2.md": [
    "/assets/2023-09-05-bs-2.e3dbdf3c.js",
    "/assets/monotonous-stack.1391d708.css"
  ],
  "assets/2023-09-05-bs-2.e3dbdf3c.js-unocss-hash.css": [
    "/assets/2023-09-05-bs-2.e3dbdf3c.js",
    "/assets/monotonous-stack.1391d708.css"
  ],
  "public/images/ds/bt/bt-pos-unrecursion.png": [
    "/assets/2023-09-05-bs-3.3d414761.js",
    "/assets/monotonous-stack.1391d708.css",
    "/assets/bt-pos-unrecursion.9a551f94.png"
  ],
  "pages/posts/algorithm/binary-tree-posts/2023-09-05-bs-3.md": [
    "/assets/2023-09-05-bs-3.3d414761.js",
    "/assets/monotonous-stack.1391d708.css",
    "/assets/bt-pos-unrecursion.9a551f94.png"
  ],
  "assets/2023-09-05-bs-3.3d414761.js-unocss-hash.css": [
    "/assets/2023-09-05-bs-3.3d414761.js",
    "/assets/monotonous-stack.1391d708.css",
    "/assets/bt-pos-unrecursion.9a551f94.png"
  ],
  "public/images/ds/bt/bt-level.png": [
    "/assets/2023-09-05-bs-4.841541b9.js",
    "/assets/monotonous-stack.1391d708.css",
    "/assets/bt-level.6b824ef6.png"
  ],
  "pages/posts/algorithm/binary-tree-posts/2023-09-05-bs-4.md": [
    "/assets/2023-09-05-bs-4.841541b9.js",
    "/assets/monotonous-stack.1391d708.css",
    "/assets/bt-level.6b824ef6.png"
  ],
  "assets/2023-09-05-bs-4.841541b9.js-unocss-hash.css": [
    "/assets/2023-09-05-bs-4.841541b9.js",
    "/assets/monotonous-stack.1391d708.css",
    "/assets/bt-level.6b824ef6.png"
  ],
  "pages/posts/algorithm/binary-tree-posts/2023-09-07-bs-1.md": [
    "/assets/2023-09-07-bs-1.41279b91.js",
    "/assets/monotonous-stack.1391d708.css"
  ],
  "assets/2023-09-07-bs-1.41279b91.js-unocss-hash.css": [
    "/assets/2023-09-07-bs-1.41279b91.js",
    "/assets/monotonous-stack.1391d708.css"
  ],
  "public/images/ds/bt/bt-serialize.png": [
    "/assets/bt-serialize.49ebd21f.js",
    "/assets/bt-serialize.9f36cf63.png"
  ],
  "public/images/ds/bt/bs-in-seralize.png": [
    "/assets/2023-09-07-bs-2.0c7f3449.js",
    "/assets/monotonous-stack.1391d708.css",
    "/assets/bs-in-seralize.d9db49e1.png"
  ],
  "pages/posts/algorithm/binary-tree-posts/2023-09-07-bs-2.md": [
    "/assets/2023-09-07-bs-2.0c7f3449.js",
    "/assets/monotonous-stack.1391d708.css",
    "/assets/bs-in-seralize.d9db49e1.png"
  ],
  "assets/2023-09-07-bs-2.0c7f3449.js-unocss-hash.css": [
    "/assets/2023-09-07-bs-2.0c7f3449.js",
    "/assets/monotonous-stack.1391d708.css",
    "/assets/bs-in-seralize.d9db49e1.png"
  ],
  "pages/posts/algorithm/binary-tree-posts/2023-09-07-bs-3.md": [
    "/assets/2023-09-07-bs-3.e083bb00.js",
    "/assets/monotonous-stack.1391d708.css"
  ],
  "assets/2023-09-07-bs-3.e083bb00.js-unocss-hash.css": [
    "/assets/2023-09-07-bs-3.e083bb00.js",
    "/assets/monotonous-stack.1391d708.css"
  ],
  "public/images/ds/bt/bt-level-seralize.png": [
    "/assets/2023-09-07-bs-4.dfbcfc0b.js",
    "/assets/monotonous-stack.1391d708.css",
    "/assets/bt-level-seralize.dd2a81c7.png"
  ],
  "pages/posts/algorithm/binary-tree-posts/2023-09-07-bs-4.md": [
    "/assets/2023-09-07-bs-4.dfbcfc0b.js",
    "/assets/monotonous-stack.1391d708.css",
    "/assets/bt-level-seralize.dd2a81c7.png"
  ],
  "assets/2023-09-07-bs-4.dfbcfc0b.js-unocss-hash.css": [
    "/assets/2023-09-07-bs-4.dfbcfc0b.js",
    "/assets/monotonous-stack.1391d708.css",
    "/assets/bt-level-seralize.dd2a81c7.png"
  ],
  "pages/posts/algorithm/binary-tree-posts/2023-09-11-bs-1.md": [
    "/assets/2023-09-11-bs-1.eb4645d9.js"
  ],
  "public/images/ds/bt/narytreebinarytreeexample.png": [
    "/assets/2023-09-11-bs-2.c5014bdf.js",
    "/assets/narytreebinarytreeexample.fcda2616.png"
  ],
  "pages/posts/algorithm/binary-tree-posts/2023-09-11-bs-2.md": [
    "/assets/2023-09-11-bs-2.c5014bdf.js",
    "/assets/narytreebinarytreeexample.fcda2616.png"
  ],
  "pages/posts/algorithm/binary-tree-posts/2023-09-11-bs-3.md": [
    "/assets/2023-09-11-bs-3.8338ba13.js"
  ],
  "public/images/ds/bt/paper-flod.png": [
    "/assets/2023-09-11-bs-4.d3a43734.js",
    "/assets/paper-flod.a2775987.png"
  ],
  "pages/posts/algorithm/binary-tree-posts/2023-09-11-bs-4.md": [
    "/assets/2023-09-11-bs-4.d3a43734.js",
    "/assets/paper-flod.a2775987.png"
  ],
  "public/images/ds/bt/bs-iscbt.png": [
    "/assets/2023-09-12-bs-1.efdb5214.js",
    "/assets/bs-iscbt.dfcbff04.png"
  ],
  "pages/posts/algorithm/binary-tree-posts/2023-09-12-bs-1.md": [
    "/assets/2023-09-12-bs-1.efdb5214.js",
    "/assets/bs-iscbt.dfcbff04.png"
  ],
  "public/images/ds/bt/bt-isbst.png": [
    "/assets/2023-09-12-bs-2.7bdcfa48.js",
    "/assets/2023-09-12-bs-2.f00fdceb.css",
    "/assets/bt-isbst.9c67f452.png"
  ],
  "pages/posts/algorithm/binary-tree-posts/2023-09-12-bs-2.md": [
    "/assets/2023-09-12-bs-2.7bdcfa48.js",
    "/assets/2023-09-12-bs-2.f00fdceb.css",
    "/assets/bt-isbst.9c67f452.png"
  ],
  "assets/2023-09-12-bs-2.7bdcfa48.js-unocss-hash.css": [
    "/assets/2023-09-12-bs-2.7bdcfa48.js",
    "/assets/2023-09-12-bs-2.f00fdceb.css",
    "/assets/bt-isbst.9c67f452.png"
  ],
  "public/images/ds/bt/bt-isBalanced.png": [
    "/assets/2023-09-12-bs-3.3209dca6.js",
    "/assets/bt-isBalanced.f50cebcf.png"
  ],
  "pages/posts/algorithm/binary-tree-posts/2023-09-12-bs-3.md": [
    "/assets/2023-09-12-bs-3.3209dca6.js",
    "/assets/bt-isBalanced.f50cebcf.png"
  ],
  "public/images/ds/bt/bs-isfull.jpg": [
    "/assets/2023-09-12-bs-4.ce78ade0.js",
    "/assets/bs-isfull.ae981e77.jpg"
  ],
  "pages/posts/algorithm/binary-tree-posts/2023-09-12-bs-4.md": [
    "/assets/2023-09-12-bs-4.ce78ade0.js",
    "/assets/bs-isfull.ae981e77.jpg"
  ],
  "pages/posts/algorithm/binary-tree-posts/2023-09-12-bs-5.md": [
    "/assets/2023-09-12-bs-5.9f10a797.js",
    "/assets/2023-09-12-bs-5.b3f0bb0d.css"
  ],
  "assets/2023-09-12-bs-5.9f10a797.js-unocss-hash.css": [
    "/assets/2023-09-12-bs-5.9f10a797.js",
    "/assets/2023-09-12-bs-5.b3f0bb0d.css"
  ],
  "public/images/ds/bt/bt-max-distance.png": [
    "/assets/2023-09-12-bs-6.d39ffffe.js",
    "/assets/2023-09-12-bs-6.58d10bd8.css",
    "/assets/bt-max-distance.decbe177.png"
  ],
  "pages/posts/algorithm/binary-tree-posts/2023-09-12-bs-6.md": [
    "/assets/2023-09-12-bs-6.d39ffffe.js",
    "/assets/2023-09-12-bs-6.58d10bd8.css",
    "/assets/bt-max-distance.decbe177.png"
  ],
  "assets/2023-09-12-bs-6.d39ffffe.js-unocss-hash.css": [
    "/assets/2023-09-12-bs-6.d39ffffe.js",
    "/assets/2023-09-12-bs-6.58d10bd8.css",
    "/assets/bt-max-distance.decbe177.png"
  ],
  "pages/posts/algorithm/binary-tree-posts/2023-09-22-bs-1.md": [
    "/assets/2023-09-22-bs-1.9557af21.js"
  ],
  "pages/posts/algorithm/binary-tree-posts/2023-09-22-bs-2.md": [
    "/assets/2023-09-22-bs-2.81fe5f1a.js",
    "/assets/2023-09-22-bs-2.a02ffdbb.css"
  ],
  "assets/2023-09-22-bs-2.81fe5f1a.js-unocss-hash.css": [
    "/assets/2023-09-22-bs-2.81fe5f1a.js",
    "/assets/2023-09-22-bs-2.a02ffdbb.css"
  ],
  "public/images/ds/bt/bs-max-happy.png": [
    "/assets/2023-09-25-bs-1.f9529f22.js",
    "/assets/computer-science-notes-chapter02.a559d910.css",
    "/assets/bs-max-happy.7dd80388.png"
  ],
  "pages/posts/algorithm/binary-tree-posts/2023-09-25-bs-1.md": [
    "/assets/2023-09-25-bs-1.f9529f22.js",
    "/assets/computer-science-notes-chapter02.a559d910.css",
    "/assets/bs-max-happy.7dd80388.png"
  ],
  "assets/2023-09-25-bs-1.f9529f22.js-unocss-hash.css": [
    "/assets/2023-09-25-bs-1.f9529f22.js",
    "/assets/computer-science-notes-chapter02.a559d910.css",
    "/assets/bs-max-happy.7dd80388.png"
  ],
  "public/images/ds/dp/dp-robot-walk.drawio.png": [
    "/assets/2023-10-23-robot-walk.a5c2f1c6.js",
    "/assets/monotonous-stack.1391d708.css",
    "/assets/dp-robot-walk.drawio.590f2e85.png"
  ],
  "pages/posts/algorithm/dp-posts/2023-10-23-robot-walk.md": [
    "/assets/2023-10-23-robot-walk.a5c2f1c6.js",
    "/assets/monotonous-stack.1391d708.css",
    "/assets/dp-robot-walk.drawio.590f2e85.png"
  ],
  "assets/2023-10-23-robot-walk.a5c2f1c6.js-unocss-hash.css": [
    "/assets/2023-10-23-robot-walk.a5c2f1c6.js",
    "/assets/monotonous-stack.1391d708.css",
    "/assets/dp-robot-walk.drawio.590f2e85.png"
  ],
  "public/images/ds/dp/dp-card.drawio.png": [
    "/assets/2023-10-24-cards-in-line.bbbcc0a7.js",
    "/assets/2023-11-17-min-coins-one-paper.0b82b164.css",
    "/assets/dp-card.drawio.af8b70f5.png"
  ],
  "pages/posts/algorithm/dp-posts/2023-10-24-cards-in-line.md": [
    "/assets/2023-10-24-cards-in-line.bbbcc0a7.js",
    "/assets/2023-11-17-min-coins-one-paper.0b82b164.css",
    "/assets/dp-card.drawio.af8b70f5.png"
  ],
  "assets/2023-10-24-cards-in-line.bbbcc0a7.js-unocss-hash.css": [
    "/assets/2023-10-24-cards-in-line.bbbcc0a7.js",
    "/assets/2023-11-17-min-coins-one-paper.0b82b164.css",
    "/assets/dp-card.drawio.af8b70f5.png"
  ],
  "pages/posts/algorithm/dp-posts/2023-10-26-k-napsack.md": [
    "/assets/2023-10-26-k-napsack.da5168f2.js",
    "/assets/2023-11-17-min-coins-one-paper.0b82b164.css"
  ],
  "assets/2023-10-26-k-napsack.da5168f2.js-unocss-hash.css": [
    "/assets/2023-10-26-k-napsack.da5168f2.js",
    "/assets/2023-11-17-min-coins-one-paper.0b82b164.css"
  ],
  "pages/posts/algorithm/dp-posts/2023-10-27-convert-to-letter-string.md": [
    "/assets/2023-10-27-convert-to-letter-string.867e1196.js",
    "/assets/monotonous-stack.1391d708.css"
  ],
  "assets/2023-10-27-convert-to-letter-string.867e1196.js-unocss-hash.css": [
    "/assets/2023-10-27-convert-to-letter-string.867e1196.js",
    "/assets/monotonous-stack.1391d708.css"
  ],
  "pages/posts/algorithm/dp-posts/2023-10-29-stickers-to-spell-word.md": [
    "/assets/2023-10-29-stickers-to-spell-word.766d1e57.js",
    "/assets/monotonous-stack.1391d708.css"
  ],
  "assets/2023-10-29-stickers-to-spell-word.766d1e57.js-unocss-hash.css": [
    "/assets/2023-10-29-stickers-to-spell-word.766d1e57.js",
    "/assets/monotonous-stack.1391d708.css"
  ],
  "pages/posts/algorithm/dp-posts/2023-10-30-longest-common-subsequence.md": [
    "/assets/2023-10-30-longest-common-subsequence.c4e474cd.js",
    "/assets/2023-10-30-longest-common-subsequence.a80f3d7f.css"
  ],
  "assets/2023-10-30-longest-common-subsequence.c4e474cd.js-unocss-hash.css": [
    "/assets/2023-10-30-longest-common-subsequence.c4e474cd.js",
    "/assets/2023-10-30-longest-common-subsequence.a80f3d7f.css"
  ],
  "public/images/ds/dp/dp-longest-palindromic-subsequence.drawio.png": [
    "/assets/2023-10-30-longest-palindromic-subsequence.d6a8b6b6.js",
    "/assets/2023-10-30-longest-palindromic-subsequence.cfee718e.css",
    "/assets/dp-longest-palindromic-subsequence.drawio.58a33ead.png"
  ],
  "pages/posts/algorithm/dp-posts/2023-10-30-longest-palindromic-subsequence.md": [
    "/assets/2023-10-30-longest-palindromic-subsequence.d6a8b6b6.js",
    "/assets/2023-10-30-longest-palindromic-subsequence.cfee718e.css",
    "/assets/dp-longest-palindromic-subsequence.drawio.58a33ead.png"
  ],
  "assets/2023-10-30-longest-palindromic-subsequence.d6a8b6b6.js-unocss-hash.css": [
    "/assets/2023-10-30-longest-palindromic-subsequence.d6a8b6b6.js",
    "/assets/2023-10-30-longest-palindromic-subsequence.cfee718e.css",
    "/assets/dp-longest-palindromic-subsequence.drawio.58a33ead.png"
  ],
  "public/images/ds/dp/dp-horse-jump.drawio.png": [
    "/assets/2023-10-31-horse-jump.266c2d56.js",
    "/assets/monotonous-stack.1391d708.css",
    "/assets/dp-horse-jump.drawio.5b91842c.png",
    "/assets/dp-horse-jump2.drawio.1501cf55.png"
  ],
  "public/images/ds/dp/dp-horse-jump2.drawio.png": [
    "/assets/2023-10-31-horse-jump.266c2d56.js",
    "/assets/monotonous-stack.1391d708.css",
    "/assets/dp-horse-jump.drawio.5b91842c.png",
    "/assets/dp-horse-jump2.drawio.1501cf55.png"
  ],
  "pages/posts/algorithm/dp-posts/2023-10-31-horse-jump.md": [
    "/assets/2023-10-31-horse-jump.266c2d56.js",
    "/assets/monotonous-stack.1391d708.css",
    "/assets/dp-horse-jump.drawio.5b91842c.png",
    "/assets/dp-horse-jump2.drawio.1501cf55.png"
  ],
  "assets/2023-10-31-horse-jump.266c2d56.js-unocss-hash.css": [
    "/assets/2023-10-31-horse-jump.266c2d56.js",
    "/assets/monotonous-stack.1391d708.css",
    "/assets/dp-horse-jump.drawio.5b91842c.png",
    "/assets/dp-horse-jump2.drawio.1501cf55.png"
  ],
  "pages/posts/algorithm/dp-posts/2023-11-03-coffee.md": [
    "/assets/2023-11-03-coffee.77469e54.js",
    "/assets/2023-11-03-coffee.c1532e49.css"
  ],
  "assets/2023-11-03-coffee.77469e54.js-unocss-hash.css": [
    "/assets/2023-11-03-coffee.77469e54.js",
    "/assets/2023-11-03-coffee.c1532e49.css"
  ],
  "pages/posts/algorithm/dp-posts/2023-11-04-min-path-sum.md": [
    "/assets/2023-11-04-min-path-sum.09ae3636.js",
    "/assets/monotonous-stack.1391d708.css"
  ],
  "assets/2023-11-04-min-path-sum.09ae3636.js-unocss-hash.css": [
    "/assets/2023-11-04-min-path-sum.09ae3636.js",
    "/assets/monotonous-stack.1391d708.css"
  ],
  "pages/posts/algorithm/dp-posts/2023-11-05-coins-way-every-pape-different.md": [
    "/assets/2023-11-05-coins-way-every-pape-different.77a1cc0a.js",
    "/assets/monotonous-stack.1391d708.css"
  ],
  "assets/2023-11-05-coins-way-every-pape-different.77a1cc0a.js-unocss-hash.css": [
    "/assets/2023-11-05-coins-way-every-pape-different.77a1cc0a.js",
    "/assets/monotonous-stack.1391d708.css"
  ],
  "public/images/ds/dp/dp-bob-die.drawio.png": [
    "/assets/2023-11-06-bob-die.c7819160.js",
    "/assets/monotonous-stack.1391d708.css",
    "/assets/dp-bob-die.drawio.d33e79ca.png",
    "/assets/dp-bob-die-2.drawio.121ec3e8.png"
  ],
  "public/images/ds/dp/dp-bob-die-2.drawio.png": [
    "/assets/2023-11-06-bob-die.c7819160.js",
    "/assets/monotonous-stack.1391d708.css",
    "/assets/dp-bob-die.drawio.d33e79ca.png",
    "/assets/dp-bob-die-2.drawio.121ec3e8.png"
  ],
  "pages/posts/algorithm/dp-posts/2023-11-06-bob-die.md": [
    "/assets/2023-11-06-bob-die.c7819160.js",
    "/assets/monotonous-stack.1391d708.css",
    "/assets/dp-bob-die.drawio.d33e79ca.png",
    "/assets/dp-bob-die-2.drawio.121ec3e8.png"
  ],
  "assets/2023-11-06-bob-die.c7819160.js-unocss-hash.css": [
    "/assets/2023-11-06-bob-die.c7819160.js",
    "/assets/monotonous-stack.1391d708.css",
    "/assets/dp-bob-die.drawio.d33e79ca.png",
    "/assets/dp-bob-die-2.drawio.121ec3e8.png"
  ],
  "pages/posts/algorithm/dp-posts/2023-11-06-coins-way-no-limit.md": [
    "/assets/2023-11-06-coins-way-no-limit.7f95a494.js",
    "/assets/monotonous-stack.1391d708.css"
  ],
  "assets/2023-11-06-coins-way-no-limit.7f95a494.js-unocss-hash.css": [
    "/assets/2023-11-06-coins-way-no-limit.7f95a494.js",
    "/assets/monotonous-stack.1391d708.css"
  ],
  "public/images/ds/dp/dp-coins-way-no-limit.drawio.png": [
    "/assets/dp-coins-way-no-limit.drawio.559a6ef2.js",
    "/assets/dp-coins-way-no-limit.drawio.9217b929.png"
  ],
  "pages/posts/algorithm/dp-posts/2023-11-06-coins-way-same-value-same-papper.md": [
    "/assets/2023-11-06-coins-way-same-value-same-papper.e4ba1db1.js",
    "/assets/monotonous-stack.1391d708.css"
  ],
  "assets/2023-11-06-coins-way-same-value-same-papper.e4ba1db1.js-unocss-hash.css": [
    "/assets/2023-11-06-coins-way-same-value-same-papper.e4ba1db1.js",
    "/assets/monotonous-stack.1391d708.css"
  ],
  "pages/posts/algorithm/dp-posts/2023-11-07-kill-monster.md": [
    "/assets/2023-11-07-kill-monster.3930c58e.js",
    "/assets/monotonous-stack.1391d708.css"
  ],
  "assets/2023-11-07-kill-monster.3930c58e.js-unocss-hash.css": [
    "/assets/2023-11-07-kill-monster.3930c58e.js",
    "/assets/monotonous-stack.1391d708.css"
  ],
  "pages/posts/algorithm/dp-posts/2023-11-07-min-coins-no-limit.md": [
    "/assets/2023-11-07-min-coins-no-limit.77f05e05.js",
    "/assets/monotonous-stack.1391d708.css"
  ],
  "assets/2023-11-07-min-coins-no-limit.77f05e05.js-unocss-hash.css": [
    "/assets/2023-11-07-min-coins-no-limit.77f05e05.js",
    "/assets/monotonous-stack.1391d708.css"
  ],
  "pages/posts/algorithm/dp-posts/2023-11-07-split-number.md": [
    "/assets/2023-11-07-split-number.9fab583c.js",
    "/assets/monotonous-stack.1391d708.css"
  ],
  "assets/2023-11-07-split-number.9fab583c.js-unocss-hash.css": [
    "/assets/2023-11-07-split-number.9fab583c.js",
    "/assets/monotonous-stack.1391d708.css"
  ],
  "public/images/ds/dp/dp-split-sum-closed-size-half.drawio.png": [
    "/assets/2023-11-10-split-sum-closed-size-half.1c441f60.js",
    "/assets/2023-11-17-min-coins-one-paper.0b82b164.css",
    "/assets/dp-split-sum-closed-size-half.drawio.0b4c26d1.png"
  ],
  "pages/posts/algorithm/dp-posts/2023-11-10-split-sum-closed-size-half.md": [
    "/assets/2023-11-10-split-sum-closed-size-half.1c441f60.js",
    "/assets/2023-11-17-min-coins-one-paper.0b82b164.css",
    "/assets/dp-split-sum-closed-size-half.drawio.0b4c26d1.png"
  ],
  "assets/2023-11-10-split-sum-closed-size-half.1c441f60.js-unocss-hash.css": [
    "/assets/2023-11-10-split-sum-closed-size-half.1c441f60.js",
    "/assets/2023-11-17-min-coins-one-paper.0b82b164.css",
    "/assets/dp-split-sum-closed-size-half.drawio.0b4c26d1.png"
  ],
  "public/images/ds/dp/dp-split-sum-closed.drawio.png": [
    "/assets/2023-11-10-split_sum_closed.87939eb0.js",
    "/assets/2023-11-17-min-coins-one-paper.0b82b164.css",
    "/assets/dp-split-sum-closed.drawio.a227d423.png"
  ],
  "pages/posts/algorithm/dp-posts/2023-11-10-split_sum_closed.md": [
    "/assets/2023-11-10-split_sum_closed.87939eb0.js",
    "/assets/2023-11-17-min-coins-one-paper.0b82b164.css",
    "/assets/dp-split-sum-closed.drawio.a227d423.png"
  ],
  "assets/2023-11-10-split_sum_closed.87939eb0.js-unocss-hash.css": [
    "/assets/2023-11-10-split_sum_closed.87939eb0.js",
    "/assets/2023-11-17-min-coins-one-paper.0b82b164.css",
    "/assets/dp-split-sum-closed.drawio.a227d423.png"
  ],
  "public/images/ds/dp/dp-n-queen.drawio.png": [
    "/assets/2023-11-13-n-queen.40efb9da.js",
    "/assets/monotonous-stack.1391d708.css",
    "/assets/dp-n-queen.drawio.3b845c6c.png"
  ],
  "pages/posts/algorithm/dp-posts/2023-11-13-n-queen.md": [
    "/assets/2023-11-13-n-queen.40efb9da.js",
    "/assets/monotonous-stack.1391d708.css",
    "/assets/dp-n-queen.drawio.3b845c6c.png"
  ],
  "assets/2023-11-13-n-queen.40efb9da.js-unocss-hash.css": [
    "/assets/2023-11-13-n-queen.40efb9da.js",
    "/assets/monotonous-stack.1391d708.css",
    "/assets/dp-n-queen.drawio.3b845c6c.png"
  ],
  "pages/posts/algorithm/graph-posts/2023-10-13-bfs.md": [
    "/assets/2023-10-13-bfs.b496a955.js",
    "/assets/monotonous-stack.1391d708.css"
  ],
  "assets/2023-10-13-bfs.b496a955.js-unocss-hash.css": [
    "/assets/2023-10-13-bfs.b496a955.js",
    "/assets/monotonous-stack.1391d708.css"
  ],
  "pages/posts/algorithm/graph-posts/2023-10-13-dfs.md": [
    "/assets/2023-10-13-dfs.a906a694.js",
    "/assets/monotonous-stack.1391d708.css"
  ],
  "assets/2023-10-13-dfs.a906a694.js-unocss-hash.css": [
    "/assets/2023-10-13-dfs.a906a694.js",
    "/assets/monotonous-stack.1391d708.css"
  ],
  "pages/posts/algorithm/graph-posts/2023-10-13-kruskal.md": [
    "/assets/2023-10-13-kruskal.24b23086.js",
    "/assets/2023-10-13-kruskal.85b22d64.css"
  ],
  "assets/2023-10-13-kruskal.24b23086.js-unocss-hash.css": [
    "/assets/2023-10-13-kruskal.24b23086.js",
    "/assets/2023-10-13-kruskal.85b22d64.css"
  ],
  "public/images/ds/graph/0000.jpg": [
    "/assets/2023-10-13-topology.f2a9e253.js",
    "/assets/monotonous-stack.1391d708.css",
    "/assets/0000.9640ba8a.jpg"
  ],
  "pages/posts/algorithm/graph-posts/2023-10-13-topology.md": [
    "/assets/2023-10-13-topology.f2a9e253.js",
    "/assets/monotonous-stack.1391d708.css",
    "/assets/0000.9640ba8a.jpg"
  ],
  "assets/2023-10-13-topology.f2a9e253.js-unocss-hash.css": [
    "/assets/2023-10-13-topology.f2a9e253.js",
    "/assets/monotonous-stack.1391d708.css",
    "/assets/0000.9640ba8a.jpg"
  ],
  "public/images/ds/graph/Dijkstra.drawio.png": [
    "/assets/2023-10-16-dijkstra.82f0438d.js",
    "/assets/monotonous-stack.1391d708.css",
    "/assets/Dijkstra.drawio.b9916d3b.png"
  ],
  "pages/posts/algorithm/graph-posts/2023-10-16-dijkstra.md": [
    "/assets/2023-10-16-dijkstra.82f0438d.js",
    "/assets/monotonous-stack.1391d708.css",
    "/assets/Dijkstra.drawio.b9916d3b.png"
  ],
  "assets/2023-10-16-dijkstra.82f0438d.js-unocss-hash.css": [
    "/assets/2023-10-16-dijkstra.82f0438d.js",
    "/assets/monotonous-stack.1391d708.css",
    "/assets/Dijkstra.drawio.b9916d3b.png"
  ],
  "public/images/ds/graph/Prim.drawio.png": [
    "/assets/2023-10-16-prim.924edff2.js",
    "/assets/monotonous-stack.1391d708.css",
    "/assets/Prim.drawio.b8596c15.png"
  ],
  "pages/posts/algorithm/graph-posts/2023-10-16-prim.md": [
    "/assets/2023-10-16-prim.924edff2.js",
    "/assets/monotonous-stack.1391d708.css",
    "/assets/Prim.drawio.b8596c15.png"
  ],
  "assets/2023-10-16-prim.924edff2.js-unocss-hash.css": [
    "/assets/2023-10-16-prim.924edff2.js",
    "/assets/monotonous-stack.1391d708.css",
    "/assets/Prim.drawio.b8596c15.png"
  ],
  "public/images/ds/greed/greed-program-01.png": [
    "/assets/2023-09-25-best_arrange.ba748890.js",
    "/assets/monotonous-stack.1391d708.css",
    "/assets/greed-program-01.576e174d.png",
    "/assets/greed-program-02.4e1beabc.png",
    "/assets/greed-program-03.d3a64b4a.png"
  ],
  "public/images/ds/greed/greed-program-02.png": [
    "/assets/2023-09-25-best_arrange.ba748890.js",
    "/assets/monotonous-stack.1391d708.css",
    "/assets/greed-program-01.576e174d.png",
    "/assets/greed-program-02.4e1beabc.png",
    "/assets/greed-program-03.d3a64b4a.png"
  ],
  "public/images/ds/greed/greed-program-03.png": [
    "/assets/2023-09-25-best_arrange.ba748890.js",
    "/assets/monotonous-stack.1391d708.css",
    "/assets/greed-program-01.576e174d.png",
    "/assets/greed-program-02.4e1beabc.png",
    "/assets/greed-program-03.d3a64b4a.png"
  ],
  "pages/posts/algorithm/greed-posts/2023-09-25-best_arrange.md": [
    "/assets/2023-09-25-best_arrange.ba748890.js",
    "/assets/monotonous-stack.1391d708.css",
    "/assets/greed-program-01.576e174d.png",
    "/assets/greed-program-02.4e1beabc.png",
    "/assets/greed-program-03.d3a64b4a.png"
  ],
  "assets/2023-09-25-best_arrange.ba748890.js-unocss-hash.css": [
    "/assets/2023-09-25-best_arrange.ba748890.js",
    "/assets/monotonous-stack.1391d708.css",
    "/assets/greed-program-01.576e174d.png",
    "/assets/greed-program-02.4e1beabc.png",
    "/assets/greed-program-03.d3a64b4a.png"
  ],
  "pages/posts/algorithm/heap-posts/2023-08-26-heap_sort.md": [
    "/assets/2023-08-26-heap_sort.7b2336b6.js"
  ],
  "pages/posts/algorithm/heap-posts/2023-08-27-heap_greater.md": [
    "/assets/2023-08-27-heap_greater.f4773421.js"
  ],
  "pages/posts/algorithm/heap-posts/2023-08-27-max_cover.md": [
    "/assets/2023-08-27-max_cover.bd337475.js"
  ],
  "pages/posts/algorithm/linked-posts/2023-08-17-linked-1.md": [
    "/assets/2023-08-17-linked-1.b03bd807.js",
    "/assets/computer-science-notes-chapter02.a559d910.css"
  ],
  "assets/2023-08-17-linked-1.b03bd807.js-unocss-hash.css": [
    "/assets/2023-08-17-linked-1.b03bd807.js",
    "/assets/computer-science-notes-chapter02.a559d910.css"
  ],
  "pages/posts/algorithm/linked-posts/2023-08-17-linked-2.md": [
    "/assets/2023-08-17-linked-2.d37124b0.js"
  ],
  "pages/posts/algorithm/linked-posts/2023-09-02-linked-1.md": [
    "/assets/2023-09-02-linked-1.ed4d7b03.js"
  ],
  "public/images/ds/linkedlistPartition1.png": [
    "/assets/2023-09-02-linked-2.59d34662.js",
    "/assets/linkedlistPartition1.8a402abf.png"
  ],
  "pages/posts/algorithm/linked-posts/2023-09-02-linked-2.md": [
    "/assets/2023-09-02-linked-2.59d34662.js",
    "/assets/linkedlistPartition1.8a402abf.png"
  ],
  "pages/posts/algorithm/linked-posts/2023-09-02-linked-3.md": [
    "/assets/2023-09-02-linked-3.21837f04.js"
  ],
  "pages/posts/algorithm/linked-posts/2023-09-02-s-f-linked.md": [
    "/assets/2023-09-02-s-f-linked.9925a1ab.js"
  ],
  "pages/posts/algorithm/linked-posts/2023-09-05-linked-1.md": [
    "/assets/2023-09-05-linked-1.8b540e59.js"
  ],
  "public/images/ds/intersectLinked2.png": [
    "/assets/2023-09-05-linked-2.214fc238.js",
    "/assets/intersectLinked2.0b54acb0.png"
  ],
  "pages/posts/algorithm/linked-posts/2023-09-05-linked-2.md": [
    "/assets/2023-09-05-linked-2.214fc238.js",
    "/assets/intersectLinked2.0b54acb0.png"
  ],
  "pages/posts/algorithm/linked-posts/2023-09-05-linked-3.md": [
    "/assets/2023-09-05-linked-3.0e28b5b1.js"
  ],
  "public/images/ds/intersectLinked.png": [
    "/assets/2023-09-05-linked-4.1b27c6d5.js",
    "/assets/intersectLinked.9bd0d202.png"
  ],
  "pages/posts/algorithm/linked-posts/2023-09-05-linked-4.md": [
    "/assets/2023-09-05-linked-4.1b27c6d5.js",
    "/assets/intersectLinked.9bd0d202.png"
  ],
  "pages/posts/algorithm/monotonous-stack-posts/2023-11-21-all-times-min-to-max.md": [
    "/assets/2023-11-21-all-times-min-to-max.4df9ac57.js",
    "/assets/monotonous-stack.1391d708.css"
  ],
  "assets/2023-11-21-all-times-min-to-max.4df9ac57.js-unocss-hash.css": [
    "/assets/2023-11-21-all-times-min-to-max.4df9ac57.js",
    "/assets/monotonous-stack.1391d708.css"
  ],
  "public/images/ds/monotonous-stack/largest-rectangle-in-histogram.png": [
    "/assets/2023-11-24-largest-rectangle-in-histogram.56320213.js",
    "/assets/largest-rectangle-in-histogram.3db28c85.png"
  ],
  "pages/posts/algorithm/monotonous-stack-posts/2023-11-24-largest-rectangle-in-histogram.md": [
    "/assets/2023-11-24-largest-rectangle-in-histogram.56320213.js",
    "/assets/largest-rectangle-in-histogram.3db28c85.png"
  ],
  "pages/posts/algorithm/queue-posts/2023-08-17-queue.md": [
    "/assets/2023-08-17-queue.a54c4bd3.js"
  ],
  "public/images/ds/recursion/hanoi.drawio.png": [
    "/assets/2023-10-18-hanoi.b9d99279.js",
    "/assets/monotonous-stack.1391d708.css",
    "/assets/hanoi.drawio.7a194534.png"
  ],
  "pages/posts/algorithm/recursion-posts/2023-10-18-hanoi.md": [
    "/assets/2023-10-18-hanoi.b9d99279.js",
    "/assets/monotonous-stack.1391d708.css",
    "/assets/hanoi.drawio.7a194534.png"
  ],
  "assets/2023-10-18-hanoi.b9d99279.js-unocss-hash.css": [
    "/assets/2023-10-18-hanoi.b9d99279.js",
    "/assets/monotonous-stack.1391d708.css",
    "/assets/hanoi.drawio.7a194534.png"
  ],
  "pages/posts/algorithm/recursion-posts/2023-10-18-print.md": [
    "/assets/2023-10-18-print.53bfad04.js",
    "/assets/monotonous-stack.1391d708.css"
  ],
  "assets/2023-10-18-print.53bfad04.js-unocss-hash.css": [
    "/assets/2023-10-18-print.53bfad04.js",
    "/assets/monotonous-stack.1391d708.css"
  ],
  "pages/posts/algorithm/recursion-posts/2023-10-20-print2.md": [
    "/assets/2023-10-20-print2.60160d15.js",
    "/assets/monotonous-stack.1391d708.css"
  ],
  "assets/2023-10-20-print2.60160d15.js-unocss-hash.css": [
    "/assets/2023-10-20-print2.60160d15.js",
    "/assets/monotonous-stack.1391d708.css"
  ],
  "pages/posts/algorithm/recursion-posts/2023-10-20-print3.md": [
    "/assets/2023-10-20-print3.f2f67f14.js",
    "/assets/monotonous-stack.1391d708.css"
  ],
  "assets/2023-10-20-print3.f2f67f14.js-unocss-hash.css": [
    "/assets/2023-10-20-print3.f2f67f14.js",
    "/assets/monotonous-stack.1391d708.css"
  ],
  "public/images/ds/recursion/reverse_stack_using_recursive.drawio.png": [
    "/assets/2023-10-23-reverse-stack.3b1befb9.js",
    "/assets/monotonous-stack.1391d708.css",
    "/assets/reverse_stack_using_recursive.drawio.f491f65d.png",
    "/assets/reverse_stack_using_recursive2.drawio.b381014d.png"
  ],
  "public/images/ds/recursion/reverse_stack_using_recursive2.drawio.png": [
    "/assets/2023-10-23-reverse-stack.3b1befb9.js",
    "/assets/monotonous-stack.1391d708.css",
    "/assets/reverse_stack_using_recursive.drawio.f491f65d.png",
    "/assets/reverse_stack_using_recursive2.drawio.b381014d.png"
  ],
  "pages/posts/algorithm/recursion-posts/2023-10-23-reverse-stack.md": [
    "/assets/2023-10-23-reverse-stack.3b1befb9.js",
    "/assets/monotonous-stack.1391d708.css",
    "/assets/reverse_stack_using_recursive.drawio.f491f65d.png",
    "/assets/reverse_stack_using_recursive2.drawio.b381014d.png"
  ],
  "assets/2023-10-23-reverse-stack.3b1befb9.js-unocss-hash.css": [
    "/assets/2023-10-23-reverse-stack.3b1befb9.js",
    "/assets/monotonous-stack.1391d708.css",
    "/assets/reverse_stack_using_recursive.drawio.f491f65d.png",
    "/assets/reverse_stack_using_recursive2.drawio.b381014d.png"
  ],
  "pages/posts/algorithm/sliding-window-posts/2023-11-13-max-window.md": [
    "/assets/2023-11-13-max-window.fb161546.js",
    "/assets/monotonous-stack.1391d708.css"
  ],
  "assets/2023-11-13-max-window.fb161546.js-unocss-hash.css": [
    "/assets/2023-11-13-max-window.fb161546.js",
    "/assets/monotonous-stack.1391d708.css"
  ],
  "pages/posts/algorithm/sliding-window-posts/2023-11-14-all-less-num-sub-array.md": [
    "/assets/2023-11-14-all-less-num-sub-array.1cce99d5.js",
    "/assets/monotonous-stack.1391d708.css"
  ],
  "assets/2023-11-14-all-less-num-sub-array.1cce99d5.js-unocss-hash.css": [
    "/assets/2023-11-14-all-less-num-sub-array.1cce99d5.js",
    "/assets/monotonous-stack.1391d708.css"
  ],
  "pages/posts/algorithm/sliding-window-posts/2023-11-17-gas-station.md": [
    "/assets/2023-11-17-gas-station.2a445173.js",
    "/assets/monotonous-stack.1391d708.css"
  ],
  "assets/2023-11-17-gas-station.2a445173.js-unocss-hash.css": [
    "/assets/2023-11-17-gas-station.2a445173.js",
    "/assets/monotonous-stack.1391d708.css"
  ],
  "pages/posts/algorithm/sliding-window-posts/2023-11-17-min-coins-one-paper.md": [
    "/assets/2023-11-17-min-coins-one-paper.1af51be7.js",
    "/assets/2023-11-17-min-coins-one-paper.0b82b164.css"
  ],
  "assets/2023-11-17-min-coins-one-paper.1af51be7.js-unocss-hash.css": [
    "/assets/2023-11-17-min-coins-one-paper.1af51be7.js",
    "/assets/2023-11-17-min-coins-one-paper.0b82b164.css"
  ],
  "public/images/ds/countingSort.gif": [
    "/assets/counting_sort.d1e30ba0.js",
    "/assets/countingSort.7dcb120c.gif"
  ],
  "pages/posts/algorithm/sort-posts/counting_sort.md": [
    "/assets/counting_sort.d1e30ba0.js",
    "/assets/countingSort.7dcb120c.gif"
  ],
  "public/images/ds/mergeSort.gif": [
    "/assets/merge_sort.ef7086a7.js",
    "/assets/2023-08-24-merge4.ba633600.css",
    "/assets/mergeSort.0764fcd0.gif"
  ],
  "pages/posts/algorithm/sort-posts/merge_sort.md": [
    "/assets/merge_sort.ef7086a7.js",
    "/assets/2023-08-24-merge4.ba633600.css",
    "/assets/mergeSort.0764fcd0.gif"
  ],
  "assets/merge_sort.ef7086a7.js-unocss-hash.css": [
    "/assets/merge_sort.ef7086a7.js",
    "/assets/2023-08-24-merge4.ba633600.css",
    "/assets/mergeSort.0764fcd0.gif"
  ],
  "public/images/ds/quickSort.gif": [
    "/assets/quick_sort.b195e7da.js",
    "/assets/quickSort.f872064c.gif"
  ],
  "pages/posts/algorithm/sort-posts/quick_sort.md": [
    "/assets/quick_sort.b195e7da.js",
    "/assets/quickSort.f872064c.gif"
  ],
  "public/images/ds/radixSort.gif": [
    "/assets/radix_sort.4d395336.js",
    "/assets/radixSort.dd93fbea.gif"
  ],
  "pages/posts/algorithm/sort-posts/radix_sort.md": [
    "/assets/radix_sort.4d395336.js",
    "/assets/radixSort.dd93fbea.gif"
  ],
  "public/images/ds/shellSort.gif": [
    "/assets/shell_sort.f1fa07d2.js",
    "/assets/shellSort.99b60f47.gif"
  ],
  "pages/posts/algorithm/sort-posts/shell_sort.md": [
    "/assets/shell_sort.f1fa07d2.js",
    "/assets/shellSort.99b60f47.gif"
  ],
  "pages/posts/algorithm/stack-posts/2023-08-17-stack-1.md": [
    "/assets/2023-08-17-stack-1.0560cbb0.js"
  ],
  "pages/posts/algorithm/stack-posts/2023-08-17-stack-2.md": [
    "/assets/2023-08-17-stack-2.6c68966b.js"
  ],
  "pages/posts/algorithm/union-set-posts/2023-10-08-union-find-2.md": [
    "/assets/2023-10-08-union-find-2.47b04a8f.js",
    "/assets/monotonous-stack.1391d708.css"
  ],
  "assets/2023-10-08-union-find-2.47b04a8f.js-unocss-hash.css": [
    "/assets/2023-10-08-union-find-2.47b04a8f.js",
    "/assets/monotonous-stack.1391d708.css"
  ],
  "pages/posts/algorithm/union-set-posts/2023-10-08-union-find.md": [
    "/assets/2023-10-08-union-find.dd53b5b1.js",
    "/assets/computer-science-notes-chapter02.a559d910.css"
  ],
  "assets/2023-10-08-union-find.dd53b5b1.js-unocss-hash.css": [
    "/assets/2023-10-08-union-find.dd53b5b1.js",
    "/assets/computer-science-notes-chapter02.a559d910.css"
  ],
  "pages/posts/algorithm/xor-posts/2023-07-18-xor.md": [
    "/assets/2023-07-18-xor.33adf413.js",
    "/assets/2023-10-13-kruskal.85b22d64.css"
  ],
  "assets/2023-07-18-xor.33adf413.js-unocss-hash.css": [
    "/assets/2023-07-18-xor.33adf413.js",
    "/assets/2023-10-13-kruskal.85b22d64.css"
  ],
  "pages/posts/algorithm/xor-posts/2023-08-16-xor.md": [
    "/assets/2023-08-16-xor.0336401f.js",
    "/assets/computer-science-notes-chapter02.a559d910.css"
  ],
  "assets/2023-08-16-xor.0336401f.js-unocss-hash.css": [
    "/assets/2023-08-16-xor.0336401f.js",
    "/assets/computer-science-notes-chapter02.a559d910.css"
  ],
  "pages/posts/ds/ds-linear-list/circular-linked.md": [
    "/assets/circular-linked.c8f576f1.js"
  ],
  "pages/posts/ds/ds-linear-list/double-linked.md": [
    "/assets/double-linked.d003d975.js"
  ],
  "pages/posts/ds/ds-linear-list/linked.md": [
    "/assets/linked.b04b50e9.js"
  ],
  "pages/posts/ds/ds-linear-list/sequence.md": [
    "/assets/sequence.2ca94ca3.js"
  ],
  "pages/posts/leetcode/01-array-post/01-two-sum.md": [
    "/assets/01-two-sum.ad31509f.js"
  ],
  "pages/posts/leetcode/01-array-post/04-median-of-two-sorted-arrays.md": [
    "/assets/04-median-of-two-sorted-arrays.207d025d.js"
  ],
  "pages/posts/leetcode/01-array-post/108-convert-sorted-array-to-binary-search-tree.md": [
    "/assets/108-convert-sorted-array-to-binary-search-tree.0e13cc2c.js"
  ],
  "pages/posts/leetcode/01-array-post/11-container-with-most-water.md": [
    "/assets/11-container-with-most-water.8f43a64f.js"
  ],
  "pages/posts/leetcode/01-array-post/118-pascals-triangle.md": [
    "/assets/118-pascals-triangle.1f56bfcf.js"
  ],
  "pages/posts/leetcode/01-array-post/119-pascals-triangle-ii.md": [
    "/assets/119-pascals-triangle-ii.3d4a017f.js"
  ],
  "pages/posts/leetcode/01-array-post/120-triangle.md": [
    "/assets/120-triangle.186b2de6.js"
  ],
  "pages/posts/leetcode/01-array-post/15-3sum.md": [
    "/assets/15-3sum.7e5d6d66.js"
  ],
  "pages/posts/leetcode/01-array-post/16-3sum-closest.md": [
    "/assets/16-3sum-closest.4f142430.js"
  ],
  "pages/posts/leetcode/01-array-post/18-4sum.md": [
    "/assets/18-4sum.05c40665.js"
  ],
  "pages/posts/leetcode/01-array-post/26-remove-duplicates-from-sorted-array.md": [
    "/assets/26-remove-duplicates-from-sorted-array.22211230.js"
  ],
  "pages/posts/leetcode/01-array-post/27-remove-element.md": [
    "/assets/27-remove-element.fbc7528b.js"
  ],
  "pages/posts/leetcode/01-array-post/31-next-permutation.md": [
    "/assets/31-next-permutation.615225b6.js"
  ],
  "pages/posts/leetcode/01-array-post/33-search-in-rotated-sorted-array.md": [
    "/assets/33-search-in-rotated-sorted-array.8149a50e.js"
  ],
  "pages/posts/leetcode/01-array-post/34-find-first-and-last-position-of-element-in-sorted-array.md": [
    "/assets/34-find-first-and-last-position-of-element-in-sorted-array.b4f7ce2f.js"
  ],
  "pages/posts/leetcode/01-array-post/35-search-insert-position.md": [
    "/assets/35-search-insert-position.1d543532.js"
  ],
  "pages/posts/leetcode/01-array-post/36-valid-sudoku.md": [
    "/assets/36-valid-sudoku.87bb22bf.js"
  ],
  "pages/posts/leetcode/01-array-post/37-sudoku-solver.md": [
    "/assets/37-sudoku-solver.5444dfb6.js"
  ],
  "pages/posts/leetcode/01-array-post/39-combination-sum.md": [
    "/assets/39-combination-sum.d805b30e.js"
  ],
  "pages/posts/leetcode/01-array-post/40-combination-sum-ii.md": [
    "/assets/40-combination-sum-ii.86618c96.js"
  ],
  "pages/posts/leetcode/01-array-post/41-first-missing-positive.md": [
    "/assets/41-first-missing-positive.2a75f5a9.js"
  ],
  "pages/posts/leetcode/01-array-post/42-trapping-rain-water.md": [
    "/assets/42-trapping-rain-water.55cd3311.js"
  ],
  "pages/posts/leetcode/01-array-post/45-jump-game-ii.md": [
    "/assets/45-jump-game-ii.9d23c848.js"
  ],
  "pages/posts/leetcode/01-array-post/46-permutations.md": [
    "/assets/46-permutations.ad3daf02.js"
  ],
  "pages/posts/leetcode/01-array-post/47-permutations-ii.md": [
    "/assets/47-permutations-ii.ad1f200c.js"
  ],
  "pages/posts/leetcode/01-array-post/48-rotate-image.md": [
    "/assets/48-rotate-image.b909ec5f.js"
  ],
  "pages/posts/leetcode/01-array-post/49-group-anagrams.md": [
    "/assets/49-group-anagrams.fc614764.js"
  ],
  "pages/posts/leetcode/01-array-post/51-n-queens.md": [
    "/assets/51-n-queens.7c658314.js"
  ],
  "pages/posts/leetcode/01-array-post/53-maximum-subarray.md": [
    "/assets/53-maximum-subarray.accdc20c.js"
  ],
  "pages/posts/leetcode/01-array-post/54-spiral-matrix.md": [
    "/assets/54-spiral-matrix.2f22c348.js"
  ],
  "pages/posts/leetcode/01-array-post/55-jump-game.md": [
    "/assets/55-jump-game.a07f095f.js"
  ],
  "pages/posts/leetcode/01-array-post/56-merge-intervals.md": [
    "/assets/56-merge-intervals.cb7ba1dc.js"
  ],
  "pages/posts/leetcode/01-array-post/57-insert-interval.md": [
    "/assets/57-insert-interval.714c68ac.js"
  ],
  "pages/posts/leetcode/01-array-post/59-spiral-matrix-ii.md": [
    "/assets/59-spiral-matrix-ii.4c506f9c.js"
  ],
  "pages/posts/leetcode/01-array-post/63-unique-paths-ii.md": [
    "/assets/63-unique-paths-ii.44d26f69.js"
  ],
  "pages/posts/leetcode/01-array-post/64-minimum-path-sum.md": [
    "/assets/64-minimum-path-sum.cfe12e15.js",
    "/assets/64-minimum-path-sum.6c547bbb.css"
  ],
  "assets/64-minimum-path-sum.cfe12e15.js-unocss-hash.css": [
    "/assets/64-minimum-path-sum.cfe12e15.js",
    "/assets/64-minimum-path-sum.6c547bbb.css"
  ],
  "pages/posts/leetcode/01-array-post/66-plus-one.md": [
    "/assets/66-plus-one.a049015b.js"
  ],
  "pages/posts/leetcode/01-array-post/68-text-justification.md": [
    "/assets/68-text-justification.848f6312.js"
  ],
  "pages/posts/leetcode/01-array-post/73-set-matrix-zeroes.md": [
    "/assets/73-set-matrix-zeroes.4f796faf.js"
  ],
  "pages/posts/leetcode/01-array-post/74-search-a-2d-matrix.md": [
    "/assets/74-search-a-2d-matrix.2ef8cb7e.js"
  ],
  "pages/posts/leetcode/01-array-post/75-sort-colors.md": [
    "/assets/75-sort-colors.9dcef2d4.js"
  ],
  "pages/posts/leetcode/01-array-post/78-subsets.md": [
    "/assets/78-subsets.8e4307b7.js"
  ],
  "pages/posts/leetcode/01-array-post/79-word-search.md": [
    "/assets/79-word-search.00818ae3.js"
  ],
  "pages/posts/leetcode/01-array-post/80-remove-duplicates-from-sorted-array-ii.md": [
    "/assets/80-remove-duplicates-from-sorted-array-ii.9034ca4f.js"
  ],
  "pages/posts/leetcode/01-array-post/81-search-in-rotated-sorted-array-ii.md": [
    "/assets/81-search-in-rotated-sorted-array-ii.02443e9c.js"
  ],
  "pages/posts/leetcode/01-array-post/85-maximal-rectangle.md": [
    "/assets/85-maximal-rectangle.2352aeb1.js"
  ],
  "pages/posts/leetcode/01-array-post/90-subsets-ii.md": [
    "/assets/90-subsets-ii.087e1185.js"
  ],
  "pages/posts/algorithm/sort-posts/merge/2023-08-21-merge.md": [
    "/assets/2023-08-21-merge.464f2ec8.js",
    "/assets/2023-08-24-merge4.ba633600.css"
  ],
  "assets/2023-08-21-merge.464f2ec8.js-unocss-hash.css": [
    "/assets/2023-08-21-merge.464f2ec8.js",
    "/assets/2023-08-24-merge4.ba633600.css"
  ],
  "pages/posts/algorithm/sort-posts/merge/2023-08-21-merge2.md": [
    "/assets/2023-08-21-merge2.9139b99d.js",
    "/assets/2023-08-24-merge4.ba633600.css"
  ],
  "assets/2023-08-21-merge2.9139b99d.js-unocss-hash.css": [
    "/assets/2023-08-21-merge2.9139b99d.js",
    "/assets/2023-08-24-merge4.ba633600.css"
  ],
  "pages/posts/algorithm/sort-posts/merge/2023-08-21-merge3.md": [
    "/assets/2023-08-21-merge3.5a29fed2.js",
    "/assets/2023-08-24-merge4.ba633600.css"
  ],
  "assets/2023-08-21-merge3.5a29fed2.js-unocss-hash.css": [
    "/assets/2023-08-21-merge3.5a29fed2.js",
    "/assets/2023-08-24-merge4.ba633600.css"
  ],
  "pages/posts/algorithm/sort-posts/merge/2023-08-24-merge4.md": [
    "/assets/2023-08-24-merge4.d30d4c1a.js",
    "/assets/2023-08-24-merge4.ba633600.css"
  ],
  "assets/2023-08-24-merge4.d30d4c1a.js-unocss-hash.css": [
    "/assets/2023-08-24-merge4.d30d4c1a.js",
    "/assets/2023-08-24-merge4.ba633600.css"
  ],
  "pages/posts/algorithm/sort-posts/quick/2023-08-25-quick_sort.md": [
    "/assets/2023-08-25-quick_sort.904e497d.js"
  ]
}